aws_cost_optimization_12/__init__.py
aws_cost_optimization_12/_cloudwatch_costing.py
aws_cost_optimization_12/_ec2_costing.py
aws_cost_optimization_12/_elb_costing.py
aws_cost_optimization_12/_kms_costing.py
aws_cost_optimization_12/_rds_costing.py
aws_cost_optimization_12/_ri_recommendations.py
aws_cost_optimization_12/_savings_plan.py
aws_cost_optimization_12/utils.py
aws_cost_optimization_12-0.2.11.dist-info/LICENCE
aws_cost_optimization_12-0.2.11.dist-info/METADATA
aws_cost_optimization_12-0.2.11.dist-info/WHEEL
aws_cost_optimization_12-0.2.11.dist-info/top_level.txt
aws_cost_optimization_12-0.2.11.dist-info/RECORD
